divisible/__init__.py
divisible/main.py
divisible-0.1.4.dist-info/WHEEL
divisible-0.1.4.dist-info/METADATA
divisible-0.1.4.dist-info/RECORD
