Metadata-Version: 2.1
Name: divisible
Version: 0.1.4
Summary: Great Python package to check for divisibility.
Home-page: https://github.com/DucNgn/divisible
Keywords: divisible,even,odd
Author: DukeNgn
Author-email: triduc2311m@gmail.com
Requires-Python: >=3.8,<4.0
Classifier: Programming Language :: Python :: 3
Classifier: Programming Language :: Python :: 3.10
Classifier: Programming Language :: Python :: 3.8
Classifier: Programming Language :: Python :: 3.9
Project-URL: Repository, https://github.com/DucNgn/divisible
